[
 {
  "size": 7,
  "grid": [
   "AGE#SNL",
   "PAC#ABE",
   "ESSENCE",
   "##TAD##",
   "WHATAMI",
   "ABS#LIL",
   "ROY#SAL"
  ],
  "answers": [
   {
    "dir": "across",
    "r": 0,
    "c": 0,
    "answer": "AGE",
    "q": 90
   },
   {
    "dir": "across",
    "r": 0,
    "c": 4,
    "answer": "SNL",
    "q": 85
   },
   {
    "dir": "across",
    "r": 1,
    "c": 0,
    "answer": "PAC",
    "q": 85
   },
   {
    "dir": "across",
    "r": 1,
    "c": 4,
    "answer": "ABE",
    "q": 80
   },
   {
    "dir": "across",
    "r": 2,
    "c": 0,
    "answer": "ESSENCE",
    "q": 90
   },
   {
    "dir": "across",
    "r": 3,
    "c": 2,
    "answer": "TAD",
    "q": 90
   },
   {
    "dir": "across",
    "r": 4,
    "c": 0,
    "answer": "WHATAMI",
    "q": 88
   },
   {
    "dir": "across",
    "r": 5,
    "c": 0,
    "answer": "ABS",
    "q": 70
   },
   {
    "dir": "across",
    "r": 5,
    "c": 4,
    "answer": "LIL",
    "q": 60
   },
   {
    "dir": "across",
    "r": 6,
    "c": 0,
    "answer": "ROY",
    "q": 80
   },
   {
    "dir": "across",
    "r": 6,
    "c": 4,
    "answer": "SAL",
    "q": 60
   },
   {
    "dir": "down",
    "r": 0,
    "c": 0,
    "answer": "APE",
    "q": 90
   },
   {
    "dir": "down",
    "r": 4,
    "c": 0,
    "answer": "WAR",
    "q": 90
   },
   {
    "dir": "down",
    "r": 0,
    "c": 1,
    "answer": "GAS",
    "q": 90
   },
   {
    "dir": "down",
    "r": 4,
    "c": 1,
    "answer": "HBO",
    "q": 80
   },
   {
    "dir": "down",
    "r": 0,
    "c": 2,
    "answer": "ECSTASY",
    "q": 90
   },
   {
    "dir": "down",
    "r": 2,
    "c": 3,
    "answer": "EAT",
    "q": 90
   },
   {
    "dir": "down",
    "r": 0,
    "c": 4,
    "answer": "SANDALS",
    "q": 80
   },
   {
    "dir": "down",
    "r": 0,
    "c": 5,
    "answer": "NBC",
    "q": 80
   },
   {
    "dir": "down",
    "r": 4,
    "c": 5,
    "answer": "MIA",
    "q": 80
   },
   {
    "dir": "down",
    "r": 0,
    "c": 6,
    "answer": "LEE",
    "q": 80
   },
   {
    "dir": "down",
    "r": 4,
    "c": 6,
    "answer": "ILL",
    "q": 90
   }
  ]
 },
 {
  "size": 7,
  "grid": [
   "###NOT#",
   "#SPIRES",
   "BAUXITE",
   "AFT#ERA",
   "GETONIT",
   "SCENTS#",
   "#ORE###"
  ],
  "answers": [
   {
    "dir": "across",
    "r": 0,
    "c": 3,
    "answer": "NOT",
    "q": 90
   },
   {
    "dir": "across",
    "r": 1,
    "c": 1,
    "answer": "SPIRES",
    "q": 80
   },
   {
    "dir": "across",
    "r": 2,
    "c": 0,
    "answer": "BAUXITE",
    "q": 90
   },
   {
    "dir": "across",
    "r": 3,
    "c": 0,
    "answer": "AFT",
    "q": 80
   },
   {
    "dir": "across",
    "r": 3,
    "c": 4,
    "answer": "ERA",
    "q": 80
   },
   {
    "dir": "across",
    "r": 4,
    "c": 0,
    "answer": "GETONIT",
    "q": 90
   },
   {
    "dir": "across",
    "r": 5,
    "c": 0,
    "answer": "SCENTS",
    "q": 80
   },
   {
    "dir": "across",
    "r": 6,
    "c": 1,
    "answer": "ORE",
    "q": 65
   },
   {
    "dir": "down",
    "r": 2,
    "c": 0,
    "answer": "BAGS",
    "q": 80
   },
   {
    "dir": "down",
    "r": 1,
    "c": 1,
    "answer": "SAFECO",
    "q": 80
   },
   {
    "dir": "down",
    "r": 1,
    "c": 2,
    "answer": "PUTTER",
    "q": 90
   },
   {
    "dir": "down",
    "r": 0,
    "c": 3,
    "answer": "NIX",
    "q": 90
   },
   {
    "dir": "down",
    "r": 4,
    "c": 3,
    "answer": "ONE",
    "q": 73
   },
   {
    "dir": "down",
    "r": 0,
    "c": 4,
    "answer": "ORIENT",
    "q": 90
   },
   {
    "dir": "down",
    "r": 0,
    "c": 5,
    "answer": "TETRIS",
    "q": 80
   },
   {
    "dir": "down",
    "r": 1,
    "c": 6,
    "answer": "SEAT",
    "q": 70
   }
  ]
 },
 {
  "size": 7,
  "grid": [
   "THE#SHY",
   "HEX#TIE",
   "CYPRESS",
   "##LOP##",
   "ANOTHER",
   "WAR#EDO",
   "WWE#NYE"
  ],
  "answers": [
   {
    "dir": "across",
    "r": 0,
    "c": 0,
    "answer": "THE",
    "q": 90
   },
   {
    "dir": "across",
    "r": 0,
    "c": 4,
    "answer": "SHY",
    "q": 90
   },
   {
    "dir": "across",
    "r": 1,
    "c": 0,
    "answer": "HEX",
    "q": 90
   },
   {
    "dir": "across",
    "r": 1,
    "c": 4,
    "answer": "TIE",
    "q": 90
   },
   {
    "dir": "across",
    "r": 2,
    "c": 0,
    "answer": "CYPRESS",
    "q": 90
   },
   {
    "dir": "across",
    "r": 3,
    "c": 2,
    "answer": "LOP",
    "q": 90
   },
   {
    "dir": "across",
    "r": 4,
    "c": 0,
    "answer": "ANOTHER",
    "q": 90
   },
   {
    "dir": "across",
    "r": 5,
    "c": 0,
    "answer": "WAR",
    "q": 90
   },
   {
    "dir": "across",
    "r": 5,
    "c": 4,
    "answer": "EDO",
    "q": 40
   },
   {
    "dir": "across",
    "r": 6,
    "c": 0,
    "answer": "WWE",
    "q": 80
   },
   {
    "dir": "across",
    "r": 6,
    "c": 4,
    "answer": "NYE",
    "q": 75
   },
   {
    "dir": "down",
    "r": 0,
    "c": 0,
    "answer": "THC",
    "q": 80
   },
   {
    "dir": "down",
    "r": 4,
    "c": 0,
    "answer": "AWW",
    "q": 85
   },
   {
    "dir": "down",
    "r": 0,
    "c": 1,
    "answer": "HEY",
    "q": 90
   },
   {
    "dir": "down",
    "r": 4,
    "c": 1,
    "answer": "NAW",
    "q": 80
   },
   {
    "dir": "down",
    "r": 0,
    "c": 2,
    "answer": "EXPLORE",
    "q": 90
   },
   {
    "dir": "down",
    "r": 2,
    "c": 3,
    "answer": "ROT",
    "q": 90
   },
   {
    "dir": "down",
    "r": 0,
    "c": 4,
    "answer": "STEPHEN",
    "q": 80
   },
   {
    "dir": "down",
    "r": 0,
    "c": 5,
    "answer": "HIS",
    "q": 90
   },
   {
    "dir": "down",
    "r": 4,
    "c": 5,
    "answer": "EDY",
    "q": 65
   },
   {
    "dir": "down",
    "r": 0,
    "c": 6,
    "answer": "YES",
    "q": 80
   },
   {
    "dir": "down",
    "r": 4,
    "c": 6,
    "answer": "ROE",
    "q": 75
   }
  ]
 },
 {
  "size": 7,
  "grid": [
   "##PROS#",
   "#IRONON",
   "#NAMELY",
   "ALL#TIE",
   "GAINED#",
   "OWNERS#",
   "#SEEM##"
  ],
  "answers": [
   {
    "dir": "across",
    "r": 0,
    "c": 2,
    "answer": "PROS",
    "q": 80
   },
   {
    "dir": "across",
    "r": 1,
    "c": 1,
    "answer": "IRONON",
    "q": 90
   },
   {
    "dir": "across",
    "r": 2,
    "c": 1,
    "answer": "NAMELY",
    "q": 90
   },
   {
    "dir": "across",
    "r": 3,
    "c": 0,
    "answer": "ALL",
    "q": 90
   },
   {
    "dir": "across",
    "r": 3,
    "c": 4,
    "answer": "TIE",
    "q": 90
   },
   {
    "dir": "across",
    "r": 4,
    "c": 0,
    "answer": "GAINED",
    "q": 80
   },
   {
    "dir": "across",
    "r": 5,
    "c": 0,
    "answer": "OWNERS",
    "q": 90
   },
   {
    "dir": "across",
    "r": 6,
    "c": 1,
    "answer": "SEEM",
    "q": 90
   },
   {
    "dir": "down",
    "r": 3,
    "c": 0,
    "answer": "AGO",
    "q": 90
   },
   {
    "dir": "down",
    "r": 1,
    "c": 1,
    "answer": "INLAWS",
    "q": 90
   },
   {
    "dir": "down",
    "r": 0,
    "c": 2,
    "answer": "PRALINE",
    "q": 90
   },
   {
    "dir": "down",
    "r": 0,
    "c": 3,
    "answer": "ROM",
    "q": 80
   },
   {
    "dir": "down",
    "r": 4,
    "c": 3,
    "answer": "NEE",
    "q": 65
   },
   {
    "dir": "down",
    "r": 0,
    "c": 4,
    "answer": "ONETERM",
    "q": 90
   },
   {
    "dir": "down",
    "r": 0,
    "c": 5,
    "answer": "SOLIDS",
    "q": 90
   },
   {
    "dir": "down",
    "r": 1,
    "c": 6,
    "answer": "NYE",
    "q": 75
   }
  ]
 },
 {
  "size": 7,
  "grid": [
   "##BREA#",
   "#FEEDS#",
   "BLEMISH",
   "FOR#TIE",
   "FOREIGN",
   "#DEMON#",
   "#SPUN##"
  ],
  "answers": [
   {
    "dir": "across",
    "r": 0,
    "c": 2,
    "answer": "BREA",
    "q": 80
   },
   {
    "dir": "across",
    "r": 1,
    "c": 1,
    "answer": "FEEDS",
    "q": 90
   },
   {
    "dir": "across",
    "r": 2,
    "c": 0,
    "answer": "BLEMISH",
    "q": 90
   },
   {
    "dir": "across",
    "r": 3,
    "c": 0,
    "answer": "FOR",
    "q": 90
   },
   {
    "dir": "across",
    "r": 3,
    "c": 4,
    "answer": "TIE",
    "q": 90
   },
   {
    "dir": "across",
    "r": 4,
    "c": 0,
    "answer": "FOREIGN",
    "q": 90
   },
   {
    "dir": "across",
    "r": 5,
    "c": 1,
    "answer": "DEMON",
    "q": 90
   },
   {
    "dir": "across",
    "r": 6,
    "c": 1,
    "answer": "SPUN",
    "q": 90
   },
   {
    "dir": "down",
    "r": 2,
    "c": 0,
    "answer": "BFF",
    "q": 60
   },
   {
    "dir": "down",
    "r": 1,
    "c": 1,
    "answer": "FLOODS",
    "q": 90
   },
   {
    "dir": "down",
    "r": 0,
    "c": 2,
    "answer": "BEERREP",
    "q": 92
   },
   {
    "dir": "down",
    "r": 0,
    "c": 3,
    "answer": "REM",
    "q": 90
   },
   {
    "dir": "down",
    "r": 4,
    "c": 3,
    "answer": "EMU",
    "q": 80
   },
   {
    "dir": "down",
    "r": 0,
    "c": 4,
    "answer": "EDITION",
    "q": 90
   },
   {
    "dir": "down",
    "r": 0,
    "c": 5,
    "answer": "ASSIGN",
    "q": 90
   },
   {
    "dir": "down",
    "r": 2,
    "c": 6,
    "answer": "HEN",
    "q": 65
   }
  ]
 },
 {
  "size": 7,
  "grid": [
   "AGE#IBM",
   "GUM#MIA",
   "ONESIZE",
   "##RUT##",
   "GASMAIN",
   "ANO#TRA",
   "SIN#EKG"
  ],
  "answers": [
   {
    "dir": "across",
    "r": 0,
    "c": 0,
    "answer": "AGE",
    "q": 90
   },
   {
    "dir": "across",
    "r": 0,
    "c": 4,
    "answer": "IBM",
    "q": 80
   },
   {
    "dir": "across",
    "r": 1,
    "c": 0,
    "answer": "GUM",
    "q": 90
   },
   {
    "dir": "across",
    "r": 1,
    "c": 4,
    "answer": "MIA",
    "q": 80
   },
   {
    "dir": "across",
    "r": 2,
    "c": 0,
    "answer": "ONESIZE",
    "q": 90
   },
   {
    "dir": "across",
    "r": 3,
    "c": 2,
    "answer": "RUT",
    "q": 90
   },
   {
    "dir": "across",
    "r": 4,
    "c": 0,
    "answer": "GASMAIN",
    "q": 90
   },
   {
    "dir": "across",
    "r": 5,
    "c": 0,
    "answer": "ANO",
    "q": 60
   },
   {
    "dir": "across",
    "r": 5,
    "c": 4,
    "answer": "TRA",
    "q": 65
   },
   {
    "dir": "across",
    "r": 6,
    "c": 0,
    "answer": "SIN",
    "q": 80
   },
   {
    "dir": "across",
    "r": 6,
    "c": 4,
    "answer": "EKG",
    "q": 65
   },
   {
    "dir": "down",
    "r": 0,
    "c": 0,
    "answer": "AGO",
    "q": 90
   },
   {
    "dir": "down",
    "r": 4,
    "c": 0,
    "answer": "GAS",
    "q": 90
   },
   {
    "dir": "down",
    "r": 0,
    "c": 1,
    "answer": "GUN",
    "q": 90
   },
   {
    "dir": "down",
    "r": 4,
    "c": 1,
    "answer": "ANI",
    "q": 60
   },
   {
    "dir": "down",
    "r": 0,
    "c": 2,
    "answer": "EMERSON",
    "q": 90
   },
   {
    "dir": "down",
    "r": 2,
    "c": 3,
    "answer": "SUM",
    "q": 90
   },
   {
    "dir": "down",
    "r": 0,
    "c": 4,
    "answer": "IMITATE",
    "q": 90
   },
   {
    "dir": "down",
    "r": 0,
    "c": 5,
    "answer": "BIZ",
    "q": 85
   },
   {
    "dir": "down",
    "r": 4,
    "c": 5,
    "answer": "IRK",
    "q": 90
   },
   {
    "dir": "down",
    "r": 0,
    "c": 6,
    "answer": "MAE",
    "q": 65
   },
   {
    "dir": "down",
    "r": 4,
    "c": 6,
    "answer": "NAG",
    "q": 90
   }
  ]
 },
 {
  "size": 7,
  "grid": [
   "NOT#OOF",
   "AIR#ADA",
   "BLUSTER",
   "##MOB##",
   "PAPYRUS",
   "ARE#AMA",
   "NIT#NAP"
  ],
  "answers": [
   {
    "dir": "across",
    "r": 0,
    "c": 0,
    "answer": "NOT",
    "q": 90
   },
   {
    "dir": "across",
    "r": 0,
    "c": 4,
    "answer": "OOF",
    "q": 80
   },
   {
    "dir": "across",
    "r": 1,
    "c": 0,
    "answer": "AIR",
    "q": 90
   },
   {
    "dir": "across",
    "r": 1,
    "c": 4,
    "answer": "ADA",
    "q": 70
   },
   {
    "dir": "across",
    "r": 2,
    "c": 0,
    "answer": "BLUSTER",
    "q": 90
   },
   {
    "dir": "across",
    "r": 3,
    "c": 2,
    "answer": "MOB",
    "q": 90
   },
   {
    "dir": "across",
    "r": 4,
    "c": 0,
    "answer": "PAPYRUS",
    "q": 90
   },
   {
    "dir": "across",
    "r": 5,
    "c": 0,
    "answer": "ARE",
    "q": 80
   },
   {
    "dir": "across",
    "r": 5,
    "c": 4,
    "answer": "AMA",
    "q": 65
   },
   {
    "dir": "across",
    "r": 6,
    "c": 0,
    "answer": "NIT",
    "q": 90
   },
   {
    "dir": "across",
    "r": 6,
    "c": 4,
    "answer": "NAP",
    "q": 80
   },
   {
    "dir": "down",
    "r": 0,
    "c": 0,
    "answer": "NAB",
    "q": 90
   },
   {
    "dir": "down",
    "r": 4,
    "c": 0,
    "answer": "PAN",
    "q": 90
   },
   {
    "dir": "down",
    "r": 0,
    "c": 1,
    "answer": "OIL",
    "q": 90
   },
   {
    "dir": "down",
    "r": 4,
    "c": 1,
    "answer": "ARI",
    "q": 65
   },
   {
    "dir": "down",
    "r": 0,
    "c": 2,
    "answer": "TRUMPET",
    "q": 90
   },
   {
    "dir": "down",
    "r": 2,
    "c": 3,
    "answer": "SOY",
    "q": 90
   },
   {
    "dir": "down",
    "r": 0,
    "c": 4,
    "answer": "OATBRAN",
    "q": 90
   },
   {
    "dir": "down",
    "r": 0,
    "c": 5,
    "answer": "ODE",
    "q": 70
   },
   {
    "dir": "down",
    "r": 4,
    "c": 5,
    "answer": "UMA",
    "q": 60
   },
   {
    "dir": "down",
    "r": 0,
    "c": 6,
    "answer": "FAR",
    "q": 90
   },
   {
    "dir": "down",
    "r": 4,
    "c": 6,
    "answer": "SAP",
    "q": 80
   }
  ]
 },
 {
  "size": 7,
  "grid": [
   "BUOY###",
   "OPPOSE#",
   "TWENTY#",
   "HAN#REM",
   "#REVILE",
   "#DRIVER",
   "###PETE"
  ],
  "answers": [
   {
    "dir": "across",
    "r": 0,
    "c": 0,
    "answer": "BUOY",
    "q": 90
   },
   {
    "dir": "across",
    "r": 1,
    "c": 0,
    "answer": "OPPOSE",
    "q": 90
   },
   {
    "dir": "across",
    "r": 2,
    "c": 0,
    "answer": "TWENTY",
    "q": 90
   },
   {
    "dir": "across",
    "r": 3,
    "c": 0,
    "answer": "HAN",
    "q": 80
   },
   {
    "dir": "across",
    "r": 3,
    "c": 4,
    "answer": "REM",
    "q": 90
   },
   {
    "dir": "across",
    "r": 4,
    "c": 1,
    "answer": "REVILE",
    "q": 90
   },
   {
    "dir": "across",
    "r": 5,
    "c": 1,
    "answer": "DRIVER",
    "q": 90
   },
   {
    "dir": "across",
    "r": 6,
    "c": 3,
    "answer": "PETE",
    "q": 70
   },
   {
    "dir": "down",
    "r": 0,
    "c": 0,
    "answer": "BOTH",
    "q": 90
   },
   {
    "dir": "down",
    "r": 0,
    "c": 1,
    "answer": "UPWARD",
    "q": 90
   },
   {
    "dir": "down",
    "r": 0,
    "c": 2,
    "answer": "OPENER",
    "q": 80
   },
   {
    "dir": "down",
    "r": 0,
    "c": 3,
    "answer": "YON",
    "q": 70
   },
   {
    "dir": "down",
    "r": 4,
    "c": 3,
    "answer": "VIP",
    "q": 80
   },
   {
    "dir": "down",
    "r": 1,
    "c": 4,
    "answer": "STRIVE",
    "q": 90
   },
   {
    "dir": "down",
    "r": 1,
    "c": 5,
    "answer": "EYELET",
    "q": 90
   },
   {
    "dir": "down",
    "r": 3,
    "c": 6,
    "answer": "MERE",
    "q": 90
   }
  ]
 }
]